{
  "res": [{
    "id": 123,
    "data": "2021-03-02",
    "hora": "10:30",
    "paciente": "Fiuk Leite",
    "local": "Klínica Conká",
    "logo": "https://www.planosempre.com.br/app/uploads/2018/07/xlogo-SUA-600x450.png.pagespeed.ic.4GzVFd7AY8.png"
  },
  {
    "id": 456,
    "data": "2021-03-02",
    "hora": "11:30",
    "paciente": "Judite Maria",
    "local": "Klínica Conká",
    "logo": ""
  },
  {
    "id": 789,
    "data": "2021-03-02",
    "hora": "14:30",
    "paciente": "Kim Kataguiri Suenaga",
    "local": "Klínica Conká",
    "logo": ""
  }]
}
